hirefire/__init__.py
hirefire/utils.py
hirefire/contrib/__init__.py
hirefire/contrib/django/__init__.py
hirefire/contrib/django/middleware.py
hirefire/contrib/flask/__init__.py
hirefire/contrib/flask/blueprint.py
hirefire/contrib/tornado/__init__.py
hirefire/contrib/tornado/handlers.py
hirefire/procs/__init__.py
hirefire/procs/celery.py
hirefire/procs/hotqueue.py
hirefire/procs/huey.py
hirefire/procs/queues.py
hirefire/procs/rq.py
tests/__init__.py
tests/contrib/__init__.py
tests/contrib/django/__init__.py
tests/contrib/django/test_middleware.py
tests/contrib/django/test_rq_proc.py
tests/contrib/django/testapp/__init__.py
tests/contrib/django/testapp/procs.py
tests/contrib/django/testapp/rq_test_procs.py
tests/contrib/django/testapp/settings.py
tests/contrib/django/testapp/urls.py
tests/contrib/flask/__init__.py
tests/contrib/flask/test_blueprint.py
HireFire-1.1.dist-info/AUTHORS.rst
HireFire-1.1.dist-info/LICENSE.txt
HireFire-1.1.dist-info/METADATA
HireFire-1.1.dist-info/WHEEL
HireFire-1.1.dist-info/top_level.txt
HireFire-1.1.dist-info/RECORD
